{
    "frames": [
        {
            "filename": "golem_idle_1",
            "frame": {
                "w": 64,
                "h": 64,
                "x": 1,
                "y": 1
            },
            "anchor": {
                "x": 0.5,
                "y": 0.5
            }
        },
        {
            "filename": "golem_idle_2",
            "frame": {
                "w": 64,
                "h": 64,
                "x": 66,
                "y": 1
            },
            "anchor": {
                "x": 0.5,
                "y": 0.5
            }
        },
        {
            "filename": "golem_idle_3",
            "frame": {
                "w": 64,
                "h": 64,
                "x": 1,
                "y": 66
            },
            "anchor": {
                "x": 0.5,
                "y": 0.5
            }
        },
        {
            "filename": "golem_idle_4",
            "frame": {
                "w": 64,
                "h": 64,
                "x": 66,
                "y": 66
            },
            "anchor": {
                "x": 0.5,
                "y": 0.5
            }
        },
        {
            "filename": "golem_idle_5",
            "frame": {
                "w": 64,
                "h": 64,
                "x": 131,
                "y": 1
            },
            "anchor": {
                "x": 0.5,
                "y": 0.5
            }
        },
        {
            "filename": "golem_idle_6",
            "frame": {
                "w": 64,
                "h": 64,
                "x": 131,
                "y": 66
            },
            "anchor": {
                "x": 0.5,
                "y": 0.5
            }
        },
        {
            "filename": "golem_walk_1",
            "frame": {
                "w": 64,
                "h": 64,
                "x": 1,
                "y": 131
            },
            "anchor": {
                "x": 0.5,
                "y": 0.5
            }
        },
        {
            "filename": "golem_walk_2",
            "frame": {
                "w": 64,
                "h": 64,
                "x": 66,
                "y": 131
            },
            "anchor": {
                "x": 0.5,
                "y": 0.5
            }
        },
        {
            "filename": "golem_walk_3",
            "frame": {
                "w": 64,
                "h": 64,
                "x": 131,
                "y": 131
            },
            "anchor": {
                "x": 0.5,
                "y": 0.5
            }
        },
        {
            "filename": "golem_walk_4",
            "frame": {
                "w": 64,
                "h": 64,
                "x": 196,
                "y": 1
            },
            "anchor": {
                "x": 0.5,
                "y": 0.5
            }
        },
        {
            "filename": "golem_walk_5",
            "frame": {
                "w": 64,
                "h": 64,
                "x": 196,
                "y": 66
            },
            "anchor": {
                "x": 0.5,
                "y": 0.5
            }
        },
        {
            "filename": "golem_walk_6",
            "frame": {
                "w": 64,
                "h": 64,
                "x": 196,
                "y": 131
            },
            "anchor": {
                "x": 0.5,
                "y": 0.5
            }
        }
    ],
    "meta": {
        "description": "Atlas generado con Atlas Packer Gamma V2",
        "web": "https://gammafp.github.io/atlas-packer-phaser/"
    }
}